aiuna/__init__.py
aiuna/_version.py
aiuna/compression.py
aiuna/history.py
aiuna/leaf.py
aiuna/content/__init__.py
aiuna/content/creation.py
aiuna/content/data.py
aiuna/content/root.py
aiuna/content/test_root.py
aiuna/mixin/__init__.py
aiuna/mixin/exceptionhandling.py
aiuna/mixin/timing.py
aiuna/step/__init__.py
aiuna/step/dataset.py
aiuna/step/delete.py
aiuna/step/file.py
aiuna/step/let.py
aiuna/step/new.py
aiuna/step/test_dataset.py
aiuna-0.2103.15.dist-info/LICENSE
aiuna-0.2103.15.dist-info/METADATA
aiuna-0.2103.15.dist-info/WHEEL
aiuna-0.2103.15.dist-info/top_level.txt
aiuna-0.2103.15.dist-info/RECORD
