Metadata-Version: 2.1
Name: aiuna
Version: 0.2103.15
Summary: Science as data transformation
Home-page: https://github.com/davips/aiuna
Author: Davi Pereira-Santos
Author-email: 
License: GPL3
Download-URL: https://github.com/davips/aiuna/releases
Platform: UNKNOWN
Classifier: Intended Audience :: Science/Research
Classifier: License :: OSI Approved :: GNU General Public License v3 (GPLv3)
Classifier: Natural Language :: English
Classifier: Programming Language :: Python
Classifier: Topic :: Scientific/Engineering
Classifier: Programming Language :: Python :: 3.8
Requires-Dist: numpy
Requires-Dist: liac-arff
Requires-Dist: lz4
Requires-Dist: zstandard
Requires-Dist: pandas
Requires-Dist: sklearn
Requires-Dist: more-itertools
Requires-Dist: akangatu
Requires-Dist: orjson
